odoo/addons/account_move_reconcile_helper/README.rst
odoo/addons/account_move_reconcile_helper/__init__.py
odoo/addons/account_move_reconcile_helper/__manifest__.py
odoo/addons/account_move_reconcile_helper/i18n/account_move_reconcile_helper.pot
odoo/addons/account_move_reconcile_helper/i18n/es.po
odoo/addons/account_move_reconcile_helper/i18n/fr.po
odoo/addons/account_move_reconcile_helper/i18n/hr.po
odoo/addons/account_move_reconcile_helper/models/__init__.py
odoo/addons/account_move_reconcile_helper/models/account_move_line.py
odoo/addons/account_move_reconcile_helper/readme/CONTRIBUTORS.rst
odoo/addons/account_move_reconcile_helper/readme/DESCRIPTION.rst
odoo/addons/account_move_reconcile_helper/static/description/icon.png
odoo/addons/account_move_reconcile_helper/static/description/index.html
odoo/addons/account_move_reconcile_helper/static/docs/journal_items.png
odoo/addons/account_move_reconcile_helper/tests/__init__.py
odoo/addons/account_move_reconcile_helper/tests/test_account_move_reconcile_helper.py
odoo/addons/account_move_reconcile_helper/views/account_move_line.xml
odoo13_addon_account_move_reconcile_helper-13.0.1.0.1.dev5.dist-info/METADATA
odoo13_addon_account_move_reconcile_helper-13.0.1.0.1.dev5.dist-info/WHEEL
odoo13_addon_account_move_reconcile_helper-13.0.1.0.1.dev5.dist-info/top_level.txt
odoo13_addon_account_move_reconcile_helper-13.0.1.0.1.dev5.dist-info/RECORD
